vidstream/__init__.py
vidstream/audio.py
vidstream/streaming.py
vidstreaming-0.0.1.dist-info/LICENSE
vidstreaming-0.0.1.dist-info/METADATA
vidstreaming-0.0.1.dist-info/WHEEL
vidstreaming-0.0.1.dist-info/top_level.txt
vidstreaming-0.0.1.dist-info/RECORD
